swibots/__init__.py
swibots/bot_app.py
swibots/config.py
swibots/errors.py
swibots/rate_limiter.py
swibots/responses.py
swibots/types.py
swibots/api/__init__.py
swibots/api/api_client.py
swibots/api/airdrop/__init__.py
swibots/api/airdrop/client.py
swibots/api/airdrop/controllers/__init__.py
swibots/api/airdrop/controllers/tournament_controller.py
swibots/api/airdrop/methods/__init__.py
swibots/api/airdrop/methods/get_referral.py
swibots/api/airdrop/methods/get_tournaments.py
swibots/api/airdrop/models/__init__.py
swibots/api/airdrop/models/referral.py
swibots/api/airdrop/models/tournament.py
swibots/api/auth/__init__.py
swibots/api/auth/auth_client.py
swibots/api/auth/methods/__init__.py
swibots/api/auth/methods/get_me.py
swibots/api/auth/models/__init__.py
swibots/api/auth/models/auth_result.py
swibots/api/auth/models/auth_user.py
swibots/api/bot/__init__.py
swibots/api/bot/bot_client.py
swibots/api/bot/controllers/__init__.py
swibots/api/bot/controllers/bot_controller.py
swibots/api/bot/controllers/game_controller.py
swibots/api/bot/methods/__init__.py
swibots/api/bot/methods/answer_callback_query.py
swibots/api/bot/methods/delete_bot_info.py
swibots/api/bot/methods/game_methods.py
swibots/api/bot/methods/get_bot_info.py
swibots/api/bot/methods/update_bot_info.py
swibots/api/bot/models/__init__.py
swibots/api/bot/models/bot_command.py
swibots/api/bot/models/bot_info.py
swibots/api/bot/models/game_info.py
swibots/api/callback/Accordian.py
swibots/api/callback/AppPage.py
swibots/api/callback/BottomBar.py
swibots/api/callback/Button.py
swibots/api/callback/Card.py
swibots/api/callback/Carousel.py
swibots/api/callback/Dropdown.py
swibots/api/callback/FAB.py
swibots/api/callback/Feed.py
swibots/api/callback/Grid.py
swibots/api/callback/Inputs.py
swibots/api/callback/ListItem.py
swibots/api/callback/ListView.py
swibots/api/callback/Players.py
swibots/api/callback/Progress.py
swibots/api/callback/Search.py
swibots/api/callback/Tab.py
swibots/api/callback/Table.py
swibots-1.4.71.dist-info/LICENSE.md
swibots-1.4.71.dist-info/METADATA
swibots-1.4.71.dist-info/WHEEL
swibots-1.4.71.dist-info/top_level.txt
swibots-1.4.71.dist-info/RECORD
