Metadata-Version: 2.2
Name: swibots
Version: 1.4.71
Summary: Bots Library for Switch
Home-page: https://github.com/switchcollab/Switch-Bots-Python-Library
Author: switchadmin
Author-email: support@switch.pe
License: LGPLv3
Requires-Python: >=3.10
License-File: LICENSE.md
Requires-Dist: httpx
Requires-Dist: websockets
Requires-Dist: aiofiles
Dynamic: author
Dynamic: author-email
Dynamic: description
Dynamic: description-content-type
Dynamic: home-page
Dynamic: license
Dynamic: requires-dist
Dynamic: requires-python
Dynamic: summary
